ChangeLog
LICENSE
MANIFEST.in
README.md
setup.py
cdmplugins/pylint/__init__.py
cdmplugins/pylint/generate.png
cdmplugins/pylint/output.png
cdmplugins/pylint/pylint.cdmp
cdmplugins/pylint/pylint.png
cdmplugins/pylint/pylintconfigdialog.py
cdmplugins/pylint/pylintdriver.py
cdmplugins/pylint/pylintoutput.py
cdmplugins/pylint/pylintresultviewer.py
cdmpylintplugin.egg-info/PKG-INFO
cdmpylintplugin.egg-info/SOURCES.txt
cdmpylintplugin.egg-info/dependency_links.txt
cdmpylintplugin.egg-info/requires.txt
cdmpylintplugin.egg-info/top_level.txt